GuineaSend.py
GuineaSender-1.0.3.data/scripts/GuineaSend.py
GuineaSender-1.0.3.dist-info/METADATA
GuineaSender-1.0.3.dist-info/WHEEL
GuineaSender-1.0.3.dist-info/top_level.txt
GuineaSender-1.0.3.dist-info/RECORD
