Metadata-Version: 2.1
Name: GuineaSender
Version: 1.0.3
Summary: Secure Messaging (less lightweight)
Home-page: https://github.com/ethicalhacker7192/OTP-MAC-online
Author: Guinea_Pig_Lord
Author-email: bear@lowrey.us
License: MIT
Keywords: Secure Messages
Platform: any
Classifier: Development Status :: 3 - Alpha
Classifier: Intended Audience :: Developers
Classifier: License :: OSI Approved :: MIT License
Classifier: Programming Language :: Python :: 3
Requires-Dist: cryptography
Requires-Dist: prompt-toolkit
